thunderbolt100k/__init__.py
thunderbolt100k/constants.py
thunderbolt100k/main.py
thunderbolt100k/libs/__init__.py
thunderbolt100k/libs/common.py
thunderbolt100k/libs/compare_time.py
thunderbolt100k/widgets/__init__.py
thunderbolt100k/widgets/weather.py
thunderbolt100k-0.1.2.dist-info/DESCRIPTION.rst
thunderbolt100k-0.1.2.dist-info/METADATA
thunderbolt100k-0.1.2.dist-info/RECORD
thunderbolt100k-0.1.2.dist-info/WHEEL
thunderbolt100k-0.1.2.dist-info/entry_points.txt
thunderbolt100k-0.1.2.dist-info/metadata.json
thunderbolt100k-0.1.2.dist-info/top_level.txt
